[
    {
        "children":[
            {
                "children":[
                    {
                        "children":[],
                        "itemStyle":{
                            "color":"#0AA3B5"
                        },
                        "name":"上证50 , 1.68%",
                        "value":1.68
                    },
                    {
                        "children":[],
                        "itemStyle":{
                            "color":"#0AA3B5"
                        },
                        "name":"50AH , 0.33%",
                        "value":0.33
                    },
                    {
                        "children":[],
                        "itemStyle":{
                            "color":"#0AA3B5"
                        },
                        "name":"沪深300 , 6.09%",
                        "value":6.09
                    },
                    {
                        "children":[],
                        "itemStyle":{
                            "color":"#0AA3B5"
                        },
                        "name":"300价值 , 3.56%",
                        "value":3.56
                    },
                    {
                        "children":[],
                        "itemStyle":{
                            "color":"#0AA3B5"
                        },
                        "name":"基本面60 , 1.95%",
                        "value":1.95
                    },
                    {
                        "children":[],
                        "itemStyle":{
                            "color":"#0AA3B5"
                        },
                        "name":"基本面120 , 2.2%",
                        "value":2.2
                    }
                ],
                "itemStyle":{
                    "color":"#0AA3B5"
                },
                "name":"大盘股 , 15.81%",
                "value":15.81
            },
            {
                "children":[
                    {
                        "children":[],
                        "itemStyle":{
                            "color":"#0AA3B5"
                        },
                        "name":"中证500 , 17.28%",
                        "value":17.28
                    },
                    {
                        "children":[],
                        "itemStyle":{
                            "color":"#0AA3B5"
                        },
                        "name":"500低波动 , 2.89%",
                        "value":2.89
                    },
                    {
                        "children":[],
                        "itemStyle":{
                            "color":"#0AA3B5"
                        },
                        "name":"中证1000 , 1.48%",
                        "value":1.48
                    },
                    {
                        "children":[],
                        "itemStyle":{
                            "color":"#0AA3B5"
                        },
                        "name":"创业板 , 3.23%",
                        "value":3.23
                    }
                ],
                "itemStyle":{
                    "color":"#0AA3B5"
                },
                "name":"中小盘股 , 24.88%",
                "value":24.88
            },
            {
                "children":[
                    {
                        "children":[],
                        "itemStyle":{
                            "color":"#0AA3B5"
                        },
                        "name":"中证红利 , 15.15%",
                        "value":15.15
                    },
                    {
                        "children":[],
                        "itemStyle":{
                            "color":"#0AA3B5"
                        },
                        "name":"标普红利 , 0.51%",
                        "value":0.51
                    }
                ],
                "itemStyle":{
                    "color":"#0AA3B5"
                },
                "name":"红利价值 , 15.65%",
                "value":15.65
            },
            {
                "children":[
                    {
                        "children":[],
                        "itemStyle":{
                            "color":"#0AA3B5"
                        },
                        "name":"养老产业 , 8.09%",
                        "value":8.09
                    },
                    {
                        "children":[],
                        "itemStyle":{
                            "color":"#0AA3B5"
                        },
                        "name":"全指医药 , 7.77%",
                        "value":7.77
                    },
                    {
                        "children":[],
                        "itemStyle":{
                            "color":"#0AA3B5"
                        },
                        "name":"中证环保 , 3.95%",
                        "value":3.95
                    },
                    {
                        "children":[],
                        "itemStyle":{
                            "color":"#0AA3B5"
                        },
                        "name":"中证传媒 , 4.21%",
                        "value":4.21
                    },
                    {
                        "children":[],
                        "itemStyle":{
                            "color":"#0AA3B5"
                        },
                        "name":"证券公司 , 0.6%",
                        "value":0.6
                    },
                    {
                        "children":[],
                        "itemStyle":{
                            "color":"#0AA3B5"
                        },
                        "name":"金融地产 , 1.21%",
                        "value":1.21
                    }
                ],
                "itemStyle":{
                    "color":"#0AA3B5"
                },
                "name":"行业股 , 25.82%",
                "value":25.82
            }
        ],
        "itemStyle":{
            "color":"#0AA3B5"
        },
        "name":"A 股 , 82.17%",
        "value":82.17
    },
    {
        "children":[
            {
                "children":[
                    {
                        "children":[],
                        "itemStyle":{
                            "color":"#BBEDA8"
                        },
                        "name":"恒生 , 0.51%",
                        "value":0.51
                    },
                    {
                        "children":[],
                        "itemStyle":{
                            "color":"#BBEDA8"
                        },
                        "name":"香港中小 , 3.25%",
                        "value":3.25
                    }
                ],
                "itemStyle":{
                    "color":"#BBEDA8"
                },
                "name":"香港 , 3.76%",
                "value":3.76
            },
            {
                "children":[
                    {
                        "children":[],
                        "itemStyle":{
                            "color":"#BBEDA8"
                        },
                        "name":"海外互联网 , 2.19%",
                        "value":2.19
                    }
                ],
                "itemStyle":{
                    "color":"#BBEDA8"
                },
                "name":"海外互联 , 2.19%",
                "value":2.19
            }
        ],
        "itemStyle":{
            "color":"#BBEDA8"
        },
        "name":"海外新兴 , 5.96%",
        "value":5.96
    },
    {
        "children":[
            {
                "children":[
                    {
                        "children":[],
                        "itemStyle":{
                            "color":"#FFC751"
                        },
                        "name":"德国30 , 2.77%",
                        "value":2.77
                    }
                ],
                "itemStyle":{
                    "color":"#FFC751"
                },
                "name":"海外成熟 , 2.77%",
                "value":2.77
            }
        ],
        "itemStyle":{
            "color":"#FFC751"
        },
        "name":"海外成熟 , 2.77%",
        "value":2.77
    },
    {
        "children":[
            {
                "children":[
                    {
                        "children":[],
                        "itemStyle":{
                            "color":"#FF8361"
                        },
                        "name":"可转债 , 6.47%",
                        "value":6.47
                    }
                ],
                "itemStyle":{
                    "color":"#FF8361"
                },
                "name":"国内债券 , 6.47%",
                "value":6.47
            }
        ],
        "itemStyle":{
            "color":"#FF8361"
        },
        "name":"债券 , 6.47%",
        "value":6.47
    },
    {
        "children":[
            {
                "children":[
                    {
                        "children":[],
                        "itemStyle":{
                            "color":"#DBB6AC"
                        },
                        "name":"黄金 , 1.09%",
                        "value":1.09
                    },
                    {
                        "children":[],
                        "itemStyle":{
                            "color":"#DBB6AC"
                        },
                        "name":"原油 , 1.55%",
                        "value":1.55
                    }
                ],
                "itemStyle":{
                    "color":"#DBB6AC"
                },
                "name":"商品 , 2.64%",
                "value":2.64
            }
        ],
        "itemStyle":{
            "color":"#DBB6AC"
        },
        "name":"商品 , 2.64%",
        "value":2.64
    },
    {
        "children":[
            {
                "children":[
                    {
                        "children":[],
                        "itemStyle":{
                            "color":"#F0DC5A"
                        },
                        "name":"货币基金 , 0.0%",
                        "value":0.0
                    }
                ],
                "itemStyle":{
                    "color":"#F0DC5A"
                },
                "name":"保本理财 , 0.0%",
                "value":0.0
            }
        ],
        "itemStyle":{
            "color":"#F0DC5A"
        },
        "name":"现金 , 0.0%",
        "value":0.0
    },
    {
        "children":[],
        "itemStyle":{
            "color":"#DCDCDC"
        },
        "name":"冻结资金 , 0.0%",
        "value":0.0
    }
]