{
    "data":[
        {
            "currentNetValue":0.0,
            "currentNetValueDate":"",
            "estimateNetValue":0.0,
            "estimateRate":0.0,
            "estimateTime":"估算时间",
            "fundCode":"999999",
            "fundName":"货币基金综合"
        },
        {
            "currentNetValue":0.0,
            "currentNetValueDate":"",
            "estimateNetValue":0.0,
            "estimateRate":0.0,
            "estimateTime":"估算时间",
            "fundCode":"999998",
            "fundName":"房地产P2P"
        },
        {
            "currentNetValue":1.624,
            "currentNetValueDate":"2019-12-10",
            "estimateNetValue":1.6241,
            "estimateRate":-0.0006,
            "estimateTime":"2019-12-10 15:00",
            "fundCode":"090010",
            "fundName":"大成中证红利指数A"
        },
        {
            "currentNetValue":1.433,
            "currentNetValueDate":"2019-12-10",
            "estimateNetValue":1.433,
            "estimateRate":-0.0021,
            "estimateTime":"2019-12-10 15:00",
            "fundCode":"519671",
            "fundName":"银河沪深300价值指数"
        },
        {
            "currentNetValue":1.4588,
            "currentNetValueDate":"2019-12-10",
            "estimateNetValue":1.4622,
            "estimateRate":-0.0021,
            "estimateTime":"2019-12-10 16:00",
            "fundCode":"501021",
            "fundName":"华宝香港中小"
        },
        {
            "currentNetValue":0.9347,
            "currentNetValueDate":"2019-12-10",
            "estimateNetValue":0.9345,
            "estimateRate":0.0037,
            "estimateTime":"2019-12-10 15:00",
            "fundCode":"003318",
            "fundName":"景顺长城中证500低波动"
        },
        {
            "currentNetValue":1.881,
            "currentNetValueDate":"2019-12-10",
            "estimateNetValue":1.8808,
            "estimateRate":-0.0007,
            "estimateTime":"2019-12-10 15:00",
            "fundCode":"070023",
            "fundName":"嘉实深证基本面120联接"
        },
        {
            "currentNetValue":2.1808,
            "currentNetValueDate":"2019-12-10",
            "estimateNetValue":2.1807,
            "estimateRate":-0.0013,
            "estimateTime":"2019-12-10 15:00",
            "fundCode":"530015",
            "fundName":"建信深证基本面60ETF联接A"
        },
        {
            "currentNetValue":0.96,
            "currentNetValueDate":"2019-12-10",
            "estimateNetValue":0.9599,
            "estimateRate":0.0049,
            "estimateTime":"2019-12-10 15:00",
            "fundCode":"000968",
            "fundName":"广发中证养老"
        },
        {
            "currentNetValue":0.9514,
            "currentNetValueDate":"2019-12-10",
            "estimateNetValue":0.9533,
            "estimateRate":0.001,
            "estimateTime":"2019-12-10 15:00",
            "fundCode":"501029",
            "fundName":"华宝红利基金"
        },
        {
            "currentNetValue":0.7673,
            "currentNetValueDate":"2019-12-10",
            "estimateNetValue":0.7669,
            "estimateRate":0.0079,
            "estimateTime":"2019-12-10 15:00",
            "fundCode":"001550",
            "fundName":"天弘中证医药100A"
        },
        {
            "currentNetValue":1.315,
            "currentNetValueDate":"2019-12-10",
            "estimateNetValue":1.3151,
            "estimateRate":0.0024,
            "estimateTime":"2019-12-10 15:00",
            "fundCode":"501050",
            "fundName":"华夏上证50AH优选指数"
        },
        {
            "currentNetValue":1.3544,
            "currentNetValueDate":"2019-12-10",
            "estimateNetValue":1.3546,
            "estimateRate":-0.0021,
            "estimateTime":"2019-12-10 15:00",
            "fundCode":"310398",
            "fundName":"申万菱信沪深300价值指数"
        },
        {
            "currentNetValue":1.253,
            "currentNetValueDate":"2019-12-10",
            "estimateNetValue":0.0,
            "estimateRate":0.0,
            "estimateTime":"估算时间",
            "fundCode":"002086",
            "fundName":"大成景安短融债券E"
        },
        {
            "currentNetValue":0.0,
            "currentNetValueDate":"",
            "estimateNetValue":0.0,
            "estimateRate":0.0,
            "estimateTime":"估算时间",
            "fundCode":"999989",
            "fundName":"住房公积金"
        },
        {
            "currentNetValue":0.0,
            "currentNetValueDate":"",
            "estimateNetValue":0.0,
            "estimateRate":0.0,
            "estimateTime":"估算时间",
            "fundCode":"999988",
            "fundName":"无息外借款"
        },
        {
            "currentNetValue":0.5599,
            "currentNetValueDate":"2019-12-10",
            "estimateNetValue":0.5598,
            "estimateRate":0.0026,
            "estimateTime":"2019-12-10 15:00",
            "fundCode":"001064",
            "fundName":"广发中证环保ETF联接基金A"
        },
        {
            "currentNetValue":2.936,
            "currentNetValueDate":"2019-12-10",
            "estimateNetValue":2.933,
            "estimateRate":0.0007,
            "estimateTime":"2019-12-10 15:00",
            "fundCode":"510050",
            "fundName":"50ETF"
        },
        {
            "currentNetValue":3.9593,
            "currentNetValueDate":"2019-12-10",
            "estimateNetValue":3.956,
            "estimateRate":0.0008,
            "estimateTime":"2019-12-10 15:00",
            "fundCode":"510300",
            "fundName":"300ETF"
        },
        {
            "currentNetValue":5.4629,
            "currentNetValueDate":"2019-12-10",
            "estimateNetValue":5.458,
            "estimateRate":0.0046,
            "estimateTime":"2019-12-10 15:00",
            "fundCode":"510500",
            "fundName":"500ETF"
        },
        {
            "currentNetValue":0.7462,
            "currentNetValueDate":"2019-12-10",
            "estimateNetValue":0.743,
            "estimateRate":0.0,
            "estimateTime":"2019-12-10 15:00",
            "fundCode":"512580",
            "fundName":"环保ETF"
        },
        {
            "currentNetValue":0.9227,
            "currentNetValueDate":"2019-12-10",
            "estimateNetValue":0.923,
            "estimateRate":-0.0011,
            "estimateTime":"2019-12-10 15:00",
            "fundCode":"512880",
            "fundName":"证券ETF"
        },
        {
            "currentNetValue":0.7833,
            "currentNetValueDate":"2019-12-10",
            "estimateNetValue":0.784,
            "estimateRate":0.0103,
            "estimateTime":"2019-12-10 15:00",
            "fundCode":"512980",
            "fundName":"传媒ETF"
        },
        {
            "currentNetValue":3.2928,
            "currentNetValueDate":"2019-12-10",
            "estimateNetValue":3.28,
            "estimateRate":0.0015,
            "estimateTime":"2019-12-10 15:00",
            "fundCode":"518880",
            "fundName":"黄金ETF"
        },
        {
            "currentNetValue":1.6692,
            "currentNetValueDate":"2019-12-10",
            "estimateNetValue":1.67,
            "estimateRate":0.0085,
            "estimateTime":"2019-12-10 15:04",
            "fundCode":"159915",
            "fundName":"创业板"
        },
        {
            "currentNetValue":1.338,
            "currentNetValueDate":"2019-12-10",
            "estimateNetValue":1.337,
            "estimateRate":0.0091,
            "estimateTime":"2019-12-10 15:04",
            "fundCode":"159938",
            "fundName":"广发医药"
        },
        {
            "currentNetValue":1.9871,
            "currentNetValueDate":"2019-12-10",
            "estimateNetValue":1.9885,
            "estimateRate":0.0047,
            "estimateTime":"2019-12-10 15:00",
            "fundCode":"000478",
            "fundName":"建信中证500指数增强A"
        },
        {
            "currentNetValue":0.5599,
            "currentNetValueDate":"2019-12-10",
            "estimateNetValue":0.5598,
            "estimateRate":0.0026,
            "estimateTime":"2019-12-10 15:00",
            "fundCode":"001064",
            "fundName":"广发中证环保ETF联接A"
        },
        {
            "currentNetValue":0.96,
            "currentNetValueDate":"2019-12-10",
            "estimateNetValue":0.9599,
            "estimateRate":0.0049,
            "estimateTime":"2019-12-10 15:00",
            "fundCode":"000968",
            "fundName":"广发养老指数A"
        },
        {
            "currentNetValue":0.561,
            "currentNetValueDate":"2019-12-10",
            "estimateNetValue":0.5606,
            "estimateRate":0.0047,
            "estimateTime":"2019-12-10 15:00",
            "fundCode":"001052",
            "fundName":"华夏中证500ETF联接A"
        },
        {
            "currentNetValue":1.104,
            "currentNetValueDate":"2019-12-10",
            "estimateNetValue":1.1044,
            "estimateRate":-0.0006,
            "estimateTime":"2019-12-10 15:00",
            "fundCode":"100032",
            "fundName":"富国中证红利指数增强"
        },
        {
            "currentNetValue":0.7855,
            "currentNetValueDate":"2019-12-10",
            "estimateNetValue":0.7854,
            "estimateRate":0.008,
            "estimateTime":"2019-12-10 15:00",
            "fundCode":"004752",
            "fundName":"广发中证传媒ETF联接A"
        },
        {
            "currentNetValue":1.7923,
            "currentNetValueDate":"2019-12-10",
            "estimateNetValue":1.7925,
            "estimateRate":0.0071,
            "estimateTime":"2019-12-10 15:00",
            "fundCode":"110026",
            "fundName":"易方达创业板ETF联接A"
        },
        {
            "currentNetValue":0.9725,
            "currentNetValueDate":"2019-12-10",
            "estimateNetValue":0.9727,
            "estimateRate":0.0071,
            "estimateTime":"2019-12-10 15:00",
            "fundCode":"003765",
            "fundName":"广发创业板ETF联接A"
        },
        {
            "currentNetValue":0.9899,
            "currentNetValueDate":"2019-12-10",
            "estimateNetValue":0.9897,
            "estimateRate":-0.0019,
            "estimateTime":"2019-12-10 15:00",
            "fundCode":"502010",
            "fundName":"易方达证券公司分级"
        },
        {
            "currentNetValue":0.381,
            "currentNetValueDate":"2019-12-09",
            "estimateNetValue":0.38,
            "estimateRate":0.0026,
            "estimateTime":"2019-12-10 15:04",
            "fundCode":"162411",
            "fundName":"华宝标普石油指数"
        },
        {
            "currentNetValue":1.307,
            "currentNetValueDate":"2019-12-09",
            "estimateNetValue":1.3161,
            "estimateRate":-0.0007,
            "estimateTime":"2019-12-11 05:00",
            "fundCode":"164906",
            "fundName":"交银中证海外中国互联网指数"
        },
        {
            "currentNetValue":1.4823,
            "currentNetValueDate":"2019-12-10",
            "estimateNetValue":1.4823,
            "estimateRate":-0.0021,
            "estimateTime":"2019-12-10 16:00",
            "fundCode":"000071",
            "fundName":"华夏恒生ETF联接A"
        },
        {
            "currentNetValue":1.198,
            "currentNetValueDate":"2019-12-09",
            "estimateNetValue":0,
            "estimateRate":0.0,
            "estimateTime":"NA",
            "fundCode":"000614",
            "fundName":"华安德国30(DAX)联接"
        },
        {
            "currentNetValue":1.9871,
            "currentNetValueDate":"2019-12-10",
            "estimateNetValue":1.9885,
            "estimateRate":0.0047,
            "estimateTime":"2019-12-10 15:00",
            "fundCode":"000478",
            "fundName":"建信中证500指数增强A"
        },
        {
            "currentNetValue":1.104,
            "currentNetValueDate":"2019-12-10",
            "estimateNetValue":1.1044,
            "estimateRate":-0.0006,
            "estimateTime":"2019-12-10 15:00",
            "fundCode":"100032",
            "fundName":"富国中证红利指数增强"
        },
        {
            "currentNetValue":1.006,
            "currentNetValueDate":"2019-12-10",
            "estimateNetValue":1.0052,
            "estimateRate":0.0012,
            "estimateTime":"2019-12-10 15:00",
            "fundCode":"001051",
            "fundName":"华夏上证50ETF联接A"
        },
        {
            "currentNetValue":0.561,
            "currentNetValueDate":"2019-12-10",
            "estimateNetValue":0.5606,
            "estimateRate":0.0047,
            "estimateTime":"2019-12-10 15:00",
            "fundCode":"001052",
            "fundName":"华夏中证500ETF联接A"
        },
        {
            "currentNetValue":0.7855,
            "currentNetValueDate":"2019-12-10",
            "estimateNetValue":0.7854,
            "estimateRate":0.008,
            "estimateTime":"2019-12-10 15:00",
            "fundCode":"004752",
            "fundName":"广发中证传媒ETF联接A"
        },
        {
            "currentNetValue":1.2191,
            "currentNetValueDate":"2019-12-10",
            "estimateNetValue":1.2124,
            "estimateRate":-0.0025,
            "estimateTime":"2019-12-11 02:29",
            "fundCode":"000216",
            "fundName":"华安黄金易ETF联接A"
        },
        {
            "currentNetValue":1.307,
            "currentNetValueDate":"2019-12-09",
            "estimateNetValue":1.3161,
            "estimateRate":-0.0007,
            "estimateTime":"2019-12-11 05:00",
            "fundCode":"164906",
            "fundName":"交银中证海外中国互联网指数"
        },
        {
            "currentNetValue":1.4823,
            "currentNetValueDate":"2019-12-10",
            "estimateNetValue":1.4823,
            "estimateRate":-0.0021,
            "estimateTime":"2019-12-10 16:00",
            "fundCode":"000071",
            "fundName":"华夏恒生ETF联接A"
        },
        {
            "currentNetValue":0.381,
            "currentNetValueDate":"2019-12-09",
            "estimateNetValue":0.38,
            "estimateRate":0.0026,
            "estimateTime":"2019-12-10 15:04",
            "fundCode":"162411",
            "fundName":"华宝标普石油指数"
        },
        {
            "currentNetValue":1.198,
            "currentNetValueDate":"2019-12-09",
            "estimateNetValue":0,
            "estimateRate":0.0,
            "estimateTime":"NA",
            "fundCode":"000614",
            "fundName":"华安德国30(DAX)联接"
        },
        {
            "currentNetValue":1.705,
            "currentNetValueDate":"2019-12-10",
            "estimateNetValue":1.6966,
            "estimateRate":0.0021,
            "estimateTime":"2019-12-10 15:00",
            "fundCode":"110027",
            "fundName":"易方达安心债券A"
        },
        {
            "currentNetValue":1.104,
            "currentNetValueDate":"2019-12-10",
            "estimateNetValue":1.1044,
            "estimateRate":-0.0006,
            "estimateTime":"2019-12-10 15:00",
            "fundCode":"100032",
            "fundName":"富国中证红利指数增强"
        },
        {
            "currentNetValue":0.96,
            "currentNetValueDate":"2019-12-10",
            "estimateNetValue":0.9599,
            "estimateRate":0.0049,
            "estimateTime":"2019-12-10 15:00",
            "fundCode":"000968",
            "fundName":"广发养老指数A"
        },
        {
            "currentNetValue":1.1671,
            "currentNetValueDate":"2019-12-10",
            "estimateNetValue":1.1576,
            "estimateRate":0.0002,
            "estimateTime":"2019-12-10 15:00",
            "fundCode":"340001",
            "fundName":"兴全可转债混合"
        },
        {
            "currentNetValue":1.705,
            "currentNetValueDate":"2019-12-10",
            "estimateNetValue":1.6966,
            "estimateRate":0.0021,
            "estimateTime":"2019-12-10 15:00",
            "fundCode":"110027",
            "fundName":"易方达安心回报债券A"
        },
        {
            "currentNetValue":0.8343,
            "currentNetValueDate":"2019-12-10",
            "estimateNetValue":0.8344,
            "estimateRate":0.008,
            "estimateTime":"2019-12-10 15:00",
            "fundCode":"001180",
            "fundName":"广发医药卫生联接A"
        },
        {
            "currentNetValue":1.198,
            "currentNetValueDate":"2019-12-09",
            "estimateNetValue":0,
            "estimateRate":0.0,
            "estimateTime":"NA",
            "fundCode":"000614",
            "fundName":"华安德国30(DAX)联接"
        },
        {
            "currentNetValue":1.625,
            "currentNetValueDate":"2019-12-10",
            "estimateNetValue":1.626,
            "estimateRate":0.0012,
            "estimateTime":"2019-12-10 15:00",
            "fundCode":"100038",
            "fundName":"富国沪深300指数增强"
        },
        {
            "currentNetValue":1.088,
            "currentNetValueDate":"2019-12-10",
            "estimateNetValue":1.088,
            "estimateRate":-0.0026,
            "estimateTime":"2019-12-10 15:00",
            "fundCode":"001469",
            "fundName":"广发中证全指金融地产联接A"
        },
        {
            "currentNetValue":1.307,
            "currentNetValueDate":"2019-12-09",
            "estimateNetValue":1.3161,
            "estimateRate":-0.0007,
            "estimateTime":"2019-12-11 05:00",
            "fundCode":"164906",
            "fundName":"交银中证海外中国互联网指数"
        },
        {
            "currentNetValue":1.636,
            "currentNetValueDate":"2019-12-10",
            "estimateNetValue":1.6376,
            "estimateRate":0.0047,
            "estimateTime":"2019-12-10 15:00",
            "fundCode":"161017",
            "fundName":"富国中证500指数(LOF)"
        },
        {
            "currentNetValue":0.381,
            "currentNetValueDate":"2019-12-09",
            "estimateNetValue":0.38,
            "estimateRate":0.0026,
            "estimateTime":"2019-12-10 15:04",
            "fundCode":"162411",
            "fundName":"华宝标普油气上游股票"
        },
        {
            "currentNetValue":1.4823,
            "currentNetValueDate":"2019-12-10",
            "estimateNetValue":1.4823,
            "estimateRate":-0.0021,
            "estimateTime":"2019-12-10 16:00",
            "fundCode":"000071",
            "fundName":"华夏恒生ETF联接A"
        },
        {
            "currentNetValue":1.347,
            "currentNetValueDate":"2019-12-09",
            "estimateNetValue":0,
            "estimateRate":0.0,
            "estimateTime":"NA",
            "fundCode":"001061",
            "fundName":"华夏收益债券(QDII)A"
        },
        {
            "currentNetValue":0.5599,
            "currentNetValueDate":"2019-12-10",
            "estimateNetValue":0.5598,
            "estimateRate":0.0026,
            "estimateTime":"2019-12-10 15:00",
            "fundCode":"001064",
            "fundName":"广发中证环保ETF联接A"
        },
        {
            "currentNetValue":1.3712,
            "currentNetValueDate":"2019-12-10",
            "estimateNetValue":1.3715,
            "estimateRate":0.0025,
            "estimateTime":"2019-12-10 15:00",
            "fundCode":"519977",
            "fundName":"长信可转债债券A"
        },
        {
            "currentNetValue":0.8842,
            "currentNetValueDate":"2019-12-10",
            "estimateNetValue":0.8845,
            "estimateRate":0.0047,
            "estimateTime":"2019-12-10 15:00",
            "fundCode":"002903",
            "fundName":"广发中证500ETF联接C"
        },
        {
            "currentNetValue":1.9871,
            "currentNetValueDate":"2019-12-10",
            "estimateNetValue":1.9885,
            "estimateRate":0.0047,
            "estimateTime":"2019-12-10 15:00",
            "fundCode":"000478",
            "fundName":"建信中证500指数增强A"
        },
        {
            "currentNetValue":0.7855,
            "currentNetValueDate":"2019-12-10",
            "estimateNetValue":0.7854,
            "estimateRate":0.008,
            "estimateTime":"2019-12-10 15:00",
            "fundCode":"004752",
            "fundName":"广发中证传媒ETF联接A"
        },
        {
            "currentNetValue":0.955,
            "currentNetValueDate":"2019-12-10",
            "estimateNetValue":0.9568,
            "estimateRate":0.0058,
            "estimateTime":"2019-12-10 15:00",
            "fundCode":"003647",
            "fundName":"创金合信中证1000指数增强C"
        },
        {
            "currentNetValue":1.0295,
            "currentNetValueDate":"2019-12-10",
            "estimateNetValue":1.0297,
            "estimateRate":0.0003,
            "estimateTime":"2019-12-10 15:00",
            "fundCode":"006793",
            "fundName":"交银稳鑫短债债券A"
        },
        {
            "currentNetValue":1.495,
            "currentNetValueDate":"2019-12-10",
            "estimateNetValue":1.493,
            "estimateRate":0.0033,
            "estimateTime":"2019-12-10 15:00",
            "fundCode":"519700",
            "fundName":"交银主题优选"
        },
        {
            "currentNetValue":1.077,
            "currentNetValueDate":"2019-12-10",
            "estimateNetValue":1.0773,
            "estimateRate":0.0003,
            "estimateTime":"2019-12-10 15:00",
            "fundCode":"519718",
            "fundName":"交银纯债A/B"
        },
        {
            "currentNetValue":1.079,
            "currentNetValueDate":"2019-12-10",
            "estimateNetValue":1.0792,
            "estimateRate":0.0002,
            "estimateTime":"2019-12-10 15:00",
            "fundCode":"519723",
            "fundName":"交银双轮动A/B"
        },
        {
            "currentNetValue":1.245,
            "currentNetValueDate":"2019-12-10",
            "estimateNetValue":1.2441,
            "estimateRate":0.0001,
            "estimateTime":"2019-12-10 15:00",
            "fundCode":"519752",
            "fundName":"交银新回报灵活配置混合A"
        },
        {
            "currentNetValue":1.293,
            "currentNetValueDate":"2019-12-10",
            "estimateNetValue":1.2915,
            "estimateRate":-0.0004,
            "estimateTime":"2019-12-10 15:00",
            "fundCode":"519755",
            "fundName":"交银多策略回报灵活配置混合A"
        },
        {
            "currentNetValue":1.0795,
            "currentNetValueDate":"2019-12-10",
            "estimateNetValue":1.0796,
            "estimateRate":0.0002,
            "estimateTime":"2019-12-10 15:00",
            "fundCode":"519776",
            "fundName":"交银裕盈纯债债券A"
        },
        {
            "currentNetValue":1.433,
            "currentNetValueDate":"2019-12-10",
            "estimateNetValue":1.433,
            "estimateRate":-0.0021,
            "estimateTime":"2019-12-10 15:00",
            "fundCode":"519671",
            "fundName":"银河沪深300价值指数"
        },
        {
            "currentNetValue":1.624,
            "currentNetValueDate":"2019-12-10",
            "estimateNetValue":1.6241,
            "estimateRate":-0.0006,
            "estimateTime":"2019-12-10 15:00",
            "fundCode":"090010",
            "fundName":"大成中证红利指数A"
        },
        {
            "currentNetValue":1.4588,
            "currentNetValueDate":"2019-12-10",
            "estimateNetValue":1.4622,
            "estimateRate":-0.0021,
            "estimateTime":"2019-12-10 16:00",
            "fundCode":"501021",
            "fundName":"华宝香港中小"
        },
        {
            "currentNetValue":0.9347,
            "currentNetValueDate":"2019-12-10",
            "estimateNetValue":0.9345,
            "estimateRate":0.0037,
            "estimateTime":"2019-12-10 15:00",
            "fundCode":"003318",
            "fundName":"景顺长城中证500低波动"
        },
        {
            "currentNetValue":1.881,
            "currentNetValueDate":"2019-12-10",
            "estimateNetValue":1.8808,
            "estimateRate":-0.0007,
            "estimateTime":"2019-12-10 15:00",
            "fundCode":"070023",
            "fundName":"嘉实深证基本面120联接"
        },
        {
            "currentNetValue":2.1808,
            "currentNetValueDate":"2019-12-10",
            "estimateNetValue":2.1807,
            "estimateRate":-0.0013,
            "estimateTime":"2019-12-10 15:00",
            "fundCode":"530015",
            "fundName":"建信深证基本面60ETF联接A"
        },
        {
            "currentNetValue":0.96,
            "currentNetValueDate":"2019-12-10",
            "estimateNetValue":0.9599,
            "estimateRate":0.0049,
            "estimateTime":"2019-12-10 15:00",
            "fundCode":"000968",
            "fundName":"广发中证养老"
        },
        {
            "currentNetValue":0.9514,
            "currentNetValueDate":"2019-12-10",
            "estimateNetValue":0.9533,
            "estimateRate":0.001,
            "estimateTime":"2019-12-10 15:00",
            "fundCode":"501029",
            "fundName":"华宝红利基金"
        },
        {
            "currentNetValue":0.7673,
            "currentNetValueDate":"2019-12-10",
            "estimateNetValue":0.7669,
            "estimateRate":0.0079,
            "estimateTime":"2019-12-10 15:00",
            "fundCode":"001550",
            "fundName":"天弘中证医药100A"
        },
        {
            "currentNetValue":1.315,
            "currentNetValueDate":"2019-12-10",
            "estimateNetValue":1.3151,
            "estimateRate":0.0024,
            "estimateTime":"2019-12-10 15:00",
            "fundCode":"501050",
            "fundName":"华夏上证50AH优选指数"
        },
        {
            "currentNetValue":1.3544,
            "currentNetValueDate":"2019-12-10",
            "estimateNetValue":1.3546,
            "estimateRate":-0.0021,
            "estimateTime":"2019-12-10 15:00",
            "fundCode":"310398",
            "fundName":"申万菱信沪深300价值指数"
        },
        {
            "currentNetValue":1.253,
            "currentNetValueDate":"2019-12-10",
            "estimateNetValue":0.0,
            "estimateRate":0.0,
            "estimateTime":"估算时间",
            "fundCode":"002086",
            "fundName":"大成景安短融债券E"
        },
        {
            "currentNetValue":1.624,
            "currentNetValueDate":"2019-12-10",
            "estimateNetValue":1.6241,
            "estimateRate":-0.0006,
            "estimateTime":"2019-12-10 15:00",
            "fundCode":"090010",
            "fundName":"大成中证红利指数A"
        },
        {
            "currentNetValue":1.433,
            "currentNetValueDate":"2019-12-10",
            "estimateNetValue":1.433,
            "estimateRate":-0.0021,
            "estimateTime":"2019-12-10 15:00",
            "fundCode":"519671",
            "fundName":"银河沪深300价值指数"
        },
        {
            "currentNetValue":1.4588,
            "currentNetValueDate":"2019-12-10",
            "estimateNetValue":1.4622,
            "estimateRate":-0.0021,
            "estimateTime":"2019-12-10 16:00",
            "fundCode":"501021",
            "fundName":"华宝香港中小"
        },
        {
            "currentNetValue":0.9347,
            "currentNetValueDate":"2019-12-10",
            "estimateNetValue":0.9345,
            "estimateRate":0.0037,
            "estimateTime":"2019-12-10 15:00",
            "fundCode":"003318",
            "fundName":"景顺长城中证500低波动"
        },
        {
            "currentNetValue":1.881,
            "currentNetValueDate":"2019-12-10",
            "estimateNetValue":1.8808,
            "estimateRate":-0.0007,
            "estimateTime":"2019-12-10 15:00",
            "fundCode":"070023",
            "fundName":"嘉实深证基本面120联接"
        },
        {
            "currentNetValue":2.1808,
            "currentNetValueDate":"2019-12-10",
            "estimateNetValue":2.1807,
            "estimateRate":-0.0013,
            "estimateTime":"2019-12-10 15:00",
            "fundCode":"530015",
            "fundName":"建信深证基本面60ETF联接A"
        },
        {
            "currentNetValue":0.96,
            "currentNetValueDate":"2019-12-10",
            "estimateNetValue":0.9599,
            "estimateRate":0.0049,
            "estimateTime":"2019-12-10 15:00",
            "fundCode":"000968",
            "fundName":"广发中证养老"
        },
        {
            "currentNetValue":0.9514,
            "currentNetValueDate":"2019-12-10",
            "estimateNetValue":0.9533,
            "estimateRate":0.001,
            "estimateTime":"2019-12-10 15:00",
            "fundCode":"501029",
            "fundName":"华宝红利基金"
        },
        {
            "currentNetValue":1.315,
            "currentNetValueDate":"2019-12-10",
            "estimateNetValue":1.3151,
            "estimateRate":0.0024,
            "estimateTime":"2019-12-10 15:00",
            "fundCode":"501050",
            "fundName":"华夏上证50AH优选指数"
        },
        {
            "currentNetValue":0.7673,
            "currentNetValueDate":"2019-12-10",
            "estimateNetValue":0.7669,
            "estimateRate":0.0079,
            "estimateTime":"2019-12-10 15:00",
            "fundCode":"001550",
            "fundName":"天弘中证医药100A"
        },
        {
            "currentNetValue":1.3544,
            "currentNetValueDate":"2019-12-10",
            "estimateNetValue":1.3546,
            "estimateRate":-0.0021,
            "estimateTime":"2019-12-10 15:00",
            "fundCode":"310398",
            "fundName":"申万菱信沪深300价值指数"
        },
        {
            "currentNetValue":1.253,
            "currentNetValueDate":"2019-12-10",
            "estimateNetValue":0.0,
            "estimateRate":0.0,
            "estimateTime":"估算时间",
            "fundCode":"002086",
            "fundName":"大成景安短融债券E"
        },
        {
            "currentNetValue":1.1068,
            "currentNetValueDate":"2019-12-10",
            "estimateNetValue":1.1071,
            "estimateRate":0.0047,
            "estimateTime":"2019-12-10 15:00",
            "fundCode":"162711",
            "fundName":"广发中证500ETF联接A"
        },
        {
            "currentNetValue":1.104,
            "currentNetValueDate":"2019-12-10",
            "estimateNetValue":1.1044,
            "estimateRate":-0.0006,
            "estimateTime":"2019-12-10 15:00",
            "fundCode":"100032",
            "fundName":"富国中证红利指数增强"
        },
        {
            "currentNetValue":0.96,
            "currentNetValueDate":"2019-12-10",
            "estimateNetValue":0.9599,
            "estimateRate":0.0049,
            "estimateTime":"2019-12-10 15:00",
            "fundCode":"000968",
            "fundName":"广发养老指数A"
        },
        {
            "currentNetValue":0.8343,
            "currentNetValueDate":"2019-12-10",
            "estimateNetValue":0.8344,
            "estimateRate":0.008,
            "estimateTime":"2019-12-10 15:00",
            "fundCode":"001180",
            "fundName":"广发医药卫生联接A"
        },
        {
            "currentNetValue":1.625,
            "currentNetValueDate":"2019-12-10",
            "estimateNetValue":1.626,
            "estimateRate":0.0012,
            "estimateTime":"2019-12-10 15:00",
            "fundCode":"100038",
            "fundName":"富国沪深300指数增强"
        },
        {
            "currentNetValue":0.7855,
            "currentNetValueDate":"2019-12-10",
            "estimateNetValue":0.7854,
            "estimateRate":0.008,
            "estimateTime":"2019-12-10 15:00",
            "fundCode":"004752",
            "fundName":"广发中证传媒ETF联接A"
        },
        {
            "currentNetValue":1.705,
            "currentNetValueDate":"2019-12-10",
            "estimateNetValue":1.6966,
            "estimateRate":0.0021,
            "estimateTime":"2019-12-10 15:00",
            "fundCode":"110027",
            "fundName":"易方达安心回报债券A"
        },
        {
            "currentNetValue":1.636,
            "currentNetValueDate":"2019-12-10",
            "estimateNetValue":1.6376,
            "estimateRate":0.0047,
            "estimateTime":"2019-12-10 15:00",
            "fundCode":"161017",
            "fundName":"富国中证500指数(LOF)"
        },
        {
            "currentNetValue":0.5599,
            "currentNetValueDate":"2019-12-10",
            "estimateNetValue":0.5598,
            "estimateRate":0.0026,
            "estimateTime":"2019-12-10 15:00",
            "fundCode":"001064",
            "fundName":"广发中证环保ETF联接A"
        },
        {
            "currentNetValue":1.198,
            "currentNetValueDate":"2019-12-09",
            "estimateNetValue":0,
            "estimateRate":0.0,
            "estimateTime":"NA",
            "fundCode":"000614",
            "fundName":"华安德国30(DAX)联接"
        },
        {
            "currentNetValue":1.7923,
            "currentNetValueDate":"2019-12-10",
            "estimateNetValue":1.7925,
            "estimateRate":0.0071,
            "estimateTime":"2019-12-10 15:00",
            "fundCode":"110026",
            "fundName":"易方达创业板ETF联接A"
        },
        {
            "currentNetValue":1.1671,
            "currentNetValueDate":"2019-12-10",
            "estimateNetValue":1.1576,
            "estimateRate":0.0002,
            "estimateTime":"2019-12-10 15:00",
            "fundCode":"340001",
            "fundName":"兴全可转债混合"
        },
        {
            "currentNetValue":1.307,
            "currentNetValueDate":"2019-12-09",
            "estimateNetValue":1.3161,
            "estimateRate":-0.0007,
            "estimateTime":"2019-12-11 05:00",
            "fundCode":"164906",
            "fundName":"交银中证海外中国互联网指数"
        },
        {
            "currentNetValue":1.006,
            "currentNetValueDate":"2019-12-10",
            "estimateNetValue":1.0052,
            "estimateRate":0.0012,
            "estimateTime":"2019-12-10 15:00",
            "fundCode":"001051",
            "fundName":"华夏上证50ETF联接A"
        },
        {
            "currentNetValue":0.381,
            "currentNetValueDate":"2019-12-09",
            "estimateNetValue":0.38,
            "estimateRate":0.0026,
            "estimateTime":"2019-12-10 15:04",
            "fundCode":"162411",
            "fundName":"华宝标普油气上游股票"
        },
        {
            "currentNetValue":0.8184,
            "currentNetValueDate":"2019-12-10",
            "estimateNetValue":0.8183,
            "estimateRate":0.0058,
            "estimateTime":"2019-12-10 15:00",
            "fundCode":"162413",
            "fundName":"华宝中证1000指数分级"
        },
        {
            "currentNetValue":1.088,
            "currentNetValueDate":"2019-12-10",
            "estimateNetValue":1.088,
            "estimateRate":-0.0026,
            "estimateTime":"2019-12-10 15:00",
            "fundCode":"001469",
            "fundName":"广发中证全指金融地产联接A"
        },
        {
            "currentNetValue":1.2191,
            "currentNetValueDate":"2019-12-10",
            "estimateNetValue":1.2124,
            "estimateRate":-0.0025,
            "estimateTime":"2019-12-11 02:29",
            "fundCode":"000216",
            "fundName":"华安黄金易ETF联接A"
        },
        {
            "currentNetValue":0.9899,
            "currentNetValueDate":"2019-12-10",
            "estimateNetValue":0.9897,
            "estimateRate":-0.0019,
            "estimateTime":"2019-12-10 15:00",
            "fundCode":"502010",
            "fundName":"易方达证券公司分级"
        },
        {
            "currentNetValue":1.3712,
            "currentNetValueDate":"2019-12-10",
            "estimateNetValue":1.3715,
            "estimateRate":0.0025,
            "estimateTime":"2019-12-10 15:00",
            "fundCode":"519977",
            "fundName":"长信可转债债券A"
        },
        {
            "currentNetValue":1.305,
            "currentNetValueDate":"2019-12-10",
            "estimateNetValue":1.3056,
            "estimateRate":0.0012,
            "estimateTime":"2019-12-10 15:00",
            "fundCode":"000051",
            "fundName":"华夏沪深300ETF联接A"
        },
        {
            "currentNetValue":1.4823,
            "currentNetValueDate":"2019-12-10",
            "estimateNetValue":1.4823,
            "estimateRate":-0.0021,
            "estimateTime":"2019-12-10 16:00",
            "fundCode":"000071",
            "fundName":"华夏恒生ETF联接A"
        },
        {
            "currentNetValue":1.9871,
            "currentNetValueDate":"2019-12-10",
            "estimateNetValue":1.9885,
            "estimateRate":0.0047,
            "estimateTime":"2019-12-10 15:00",
            "fundCode":"000478",
            "fundName":"建信中证500指数增强A"
        },
        {
            "currentNetValue":0.8842,
            "currentNetValueDate":"2019-12-10",
            "estimateNetValue":0.8845,
            "estimateRate":0.0047,
            "estimateTime":"2019-12-10 15:00",
            "fundCode":"002903",
            "fundName":"广发中证500ETF联接C"
        }
    ],
    "updateTime":"2019-12-11 08:39:46"
}